[
    {
        "Version": "1.1",
        "TranDtls": {
            "TaxSch": "GST",
            "SupTyp": "EXPWOP",
            "IgstOnIntra": "N",
            "RegRev": "N",
            "EcmGstin": null
        },
        "DocDtls": {
            "Typ": "INV",
            "No": "IN-058/11/2022",
            "Dt": "23/11/2022"
        },
        "SellerDtls": {
            "Gstin": "19AAECS6338L1ZT",
            "LglNm": "SHILPA OVERSEAS PVT. LTD.",
            "TrdNm": "SHILPA OVERSEAS PVT. LTD.",
            "Addr1": "51, MAHANIRBAN ROAD",
            "Addr2": "KOLKATA",
            "Loc": "WEST BENGAL",
            "Pin": 700029,
            "Stcd": "19",
            "Ph": "03340031411",
            "Em": "deep.paul@shilpaoverseas.com"
        },
        "BuyerDtls": {
            "Gstin": "URP",
            "LglNm": "H.J. DE ROOY LEDERWAREN B.V.",
            "TrdNm": "H.J. DE ROOY LEDERWAREN B.V.",
            "Pos": "96",
            "Addr1": "ELZENWEG 29,  5144 MB WAALWIJK",
            "Addr2": null,
            "Loc": "THE NETHERLANDS",
            "Pin": 999999,
            "Stcd": "96",
            "Ph": null,
            "Em": null
        },
        "DispDtls": null,
        "ShipDtls": null,
        "ValDtls": {
            "AssVal": 3605097.6,
            "IgstVal": 0,
            "CgstVal": 0,
            "SgstVal": 0,
            "CesVal": 0,
            "StCesVal": 0,
            "Discount": 324459.2,
            "OthChrg": 0,
            "RndOffAmt": 0,
            "TotInvVal": 3280638.4,
            "TotInvValFc": 39430.75
        },
        "ExpDtls": {
            "ShipBNo": null,
            "ShipBdt": null,
            "Port": null,
            "RefClm": null,
            "ForCur": "EUR",
            "CntCode": null,
            "ExpDuty": null
        },
        "EwbDtls": {
            "TransId": null,
            "TransName": "20CUBE",
            "TransMode": "4",
            "Distance": 100,
            "TransDocNo": null,
            "TransDocDt": null,
            "VehNo": null,
            "VehType": null
        },
        "PayDtls": null,
        "RefDtls": null,
        "AddlDocDtls": null,
        "ItemList": [
            {
                "SlNo": "1",
                "PrdDesc": "PURSE",
                "IsServc": "N",
                "HsnCd": "42023120",
                "Barcde": null,
                "Qty": 600,
                "FreeQty": 0,
                "Unit": "PCS",
                "UnitPrice": 449.28,
                "TotAmt": 269568,
                "Discount": 0,
                "PreTaxVal": 0,
                "AssAmt": 269568,
                "GstRt": 0,
                "IgstAmt": 0,
                "CgstAmt": 0,
                "SgstAmt": 0,
                "CesRt": 0,
                "CesAmt": 0,
                "CesNonAdvlAmt": 0,
                "StateCesRt": 0,
                "StateCesAmt": 0,
                "StateCesNonAdvlAmt": 0,
                "OthChrg": 0,
                "TotItemVal": 269568,
                "OrdLineRef": null,
                "OrgCntry": null,
                "PrdSlNo": null,
                "BchDtls": null,
                "AttribDtls": null
            },
            {
                "SlNo": "2",
                "PrdDesc": "CARD HOLDER",
                "IsServc": "N",
                "HsnCd": "42050090",
                "Barcde": null,
                "Qty": 2400,
                "FreeQty": 0,
                "Unit": "PCS",
                "UnitPrice": 257.92,
                "TotAmt": 619008,
                "Discount": 0,
                "PreTaxVal": 0,
                "AssAmt": 619008,
                "GstRt": 0,
                "IgstAmt": 0,
                "CgstAmt": 0,
                "SgstAmt": 0,
                "CesRt": 0,
                "CesAmt": 0,
                "CesNonAdvlAmt": 0,
                "StateCesRt": 0,
                "StateCesAmt": 0,
                "StateCesNonAdvlAmt": 0,
                "OthChrg": 0,
                "TotItemVal": 619008,
                "OrdLineRef": null,
                "OrgCntry": null,
                "PrdSlNo": null,
                "BchDtls": null,
                "AttribDtls": null
            },
            {
                "SlNo": "3",
                "PrdDesc": "CARD HOLDER",
                "IsServc": "N",
                "HsnCd": "42050090",
                "Barcde": null,
                "Qty": 1200,
                "FreeQty": 0,
                "Unit": "PCS",
                "UnitPrice": 120.64,
                "TotAmt": 144768,
                "Discount": 0,
                "PreTaxVal": 0,
                "AssAmt": 144768,
                "GstRt": 0,
                "IgstAmt": 0,
                "CgstAmt": 0,
                "SgstAmt": 0,
                "CesRt": 0,
                "CesAmt": 0,
                "CesNonAdvlAmt": 0,
                "StateCesRt": 0,
                "StateCesAmt": 0,
                "StateCesNonAdvlAmt": 0,
                "OthChrg": 0,
                "TotItemVal": 144768,
                "OrdLineRef": null,
                "OrgCntry": null,
                "PrdSlNo": null,
                "BchDtls": null,
                "AttribDtls": null
            },
            {
                "SlNo": "4",
                "PrdDesc": "WALLET",
                "IsServc": "N",
                "HsnCd": "42023120",
                "Barcde": null,
                "Qty": 4500,
                "FreeQty": 0,
                "Unit": "PCS",
                "UnitPrice": 416,
                "TotAmt": 1872000,
                "Discount": 0,
                "PreTaxVal": 0,
                "AssAmt": 1872000,
                "GstRt": 0,
                "IgstAmt": 0,
                "CgstAmt": 0,
                "SgstAmt": 0,
                "CesRt": 0,
                "CesAmt": 0,
                "CesNonAdvlAmt": 0,
                "StateCesRt": 0,
                "StateCesAmt": 0,
                "StateCesNonAdvlAmt": 0,
                "OthChrg": 0,
                "TotItemVal": 1872000,
                "OrdLineRef": null,
                "OrgCntry": null,
                "PrdSlNo": null,
                "BchDtls": null,
                "AttribDtls": null
            },
            {
                "SlNo": "5",
                "PrdDesc": "WALLET",
                "IsServc": "N",
                "HsnCd": "42023120",
                "Barcde": null,
                "Qty": 1890,
                "FreeQty": 0,
                "Unit": "PCS",
                "UnitPrice": 370.24,
                "TotAmt": 699753.6,
                "Discount": 0,
                "PreTaxVal": 0,
                "AssAmt": 699753.6,
                "GstRt": 0,
                "IgstAmt": 0,
                "CgstAmt": 0,
                "SgstAmt": 0,
                "CesRt": 0,
                "CesAmt": 0,
                "CesNonAdvlAmt": 0,
                "StateCesRt": 0,
                "StateCesAmt": 0,
                "StateCesNonAdvlAmt": 0,
                "OthChrg": 0,
                "TotItemVal": 699753.6,
                "OrdLineRef": null,
                "OrgCntry": null,
                "PrdSlNo": null,
                "BchDtls": null,
                "AttribDtls": null
            }
        ]
    }
]